run_if_changed/__init__.py
run_if_changed/change_detection.py
run_if_changed/cli.py
run_if_changed-0.5.1.dist-info/METADATA
run_if_changed-0.5.1.dist-info/WHEEL
run_if_changed-0.5.1.dist-info/entry_points.txt
run_if_changed-0.5.1.dist-info/RECORD
