Metadata-Version: 2.1
Name: run-if-changed
Version: 0.5.1
Summary: 
Author: CD Clark III
Author-email: clifton.clark@gmail.com
Requires-Python: >=3.10,<4.0
Classifier: Programming Language :: Python :: 3
Classifier: Programming Language :: Python :: 3.10
Classifier: Programming Language :: Python :: 3.11
Classifier: Programming Language :: Python :: 3.12
Requires-Dist: typer (>=0.12.3,<0.13.0)
